README
setup.py
django_superview.egg-info/PKG-INFO
django_superview.egg-info/SOURCES.txt
django_superview.egg-info/dependency_links.txt
django_superview.egg-info/requires.txt
django_superview.egg-info/top_level.txt
superview/__init__.py
superview/menu.py
superview/settings.py
superview/stream.py
superview/utils.py
superview/views.py
superview/templatetags/__init__.py
superview/templatetags/superview.py