Metadata-Version: 1.1
Name: django-superview
Version: 0.3.6
Summary: Generic View class with extra funionality for Django
Home-page: https://github.com/jespino/django-superview
Author: Jesús Espino García & Andrei Antoukh
Author-email: jespinog@gmail.com, niwi@niwi.be
License: BSD
Keywords: django,view
Platform: UNKNOWN
Classifier: Programming Language :: Python
Classifier: Development Status :: 4 - Beta
Classifier: Framework :: Django
Classifier: Intended Audience :: Developers
Classifier: License :: OSI Approved :: BSD License
Classifier: Operating System :: OS Independent
Classifier: Programming Language :: Python
Classifier: Topic :: Internet :: WWW/HTTP
Classifier: Programming Language :: Python :: 2.6
Classifier: Programming Language :: Python :: 2.7
